{
  "ticker": "BKNG",
  "name": "Booking Holdings Inc. Common Stock",
  "market": "stocks",
  "locale": "us",
  "primary_exchange": "XNAS",
  "type": "CS",
  "active": true,
  "currency_name": "usd",
  "cik": "0001075531",
  "composite_figi": "BBG000BLBVN4",
  "share_class_figi": "BBG001S89N72",
  "market_cap": 132992385970.68,
  "phone_number": "203-299-8000",
  "address": {
    "address1": "800 CONNECTICUT AVE",
    "city": "NORWALK",
    "state": "CT",
    "postal_code": "06854"
  },
  "description": "Booking is the world's largest online travel agency by sales, offering booking and payment services for hotel and alternative accommodation rooms, airlines, rental cars, restaurants, cruises, experiences, and other vacation packages. The company operates several branded travel booking sites, including Booking.com, Agoda, OpenTable, Rentalcars.com, and Kayak. Transaction fees for online bookings account for the bulk of revenue and profits.",
  "sic_code": "4700",
  "sic_description": "TRANSPORTATION SERVICES",
  "ticker_root": "BKNG",
  "homepage_url": "https://www.bookingholdings.com",
  "total_employees": 24300,
  "list_date": "1999-03-31",
  "branding": {
    "logo_url": "https://api.polygon.io/v1/reference/company-branding/Ym9va2luZ2hvbGRpbmdzLmNvbQ/images/2025-04-04_logo.svg",
    "icon_url": "https://api.polygon.io/v1/reference/company-branding/Ym9va2luZ2hvbGRpbmdzLmNvbQ/images/2025-04-04_icon.jpeg"
  },
  "share_class_shares_outstanding": 774878436,
  "weighted_shares_outstanding": 774878436,
  "round_lot": 10
}