{
  "ticker": "BLDP",
  "name": "Ballard Power Systems Inc.",
  "market": "stocks",
  "locale": "us",
  "primary_exchange": "XNAS",
  "type": "CS",
  "active": true,
  "currency_name": "usd",
  "cik": "0001453015",
  "composite_figi": "BBG000BNJRZ8",
  "share_class_figi": "BBG001S5Y1D1",
  "market_cap": 1317449460.13,
  "description": "Ballard Power Systems Inc is engaged in design, development, manufacture, sale and service of proton exchange membrane (\"PEM\") fuel cell products for a variety of applications, focusing on power products for bus, truck, rail, marine, stationary and emerging market (material handling, off-road and other) applications, as well as the delivery of services, including technology solutions, after sales services and training. A fuel cell is an environmentally clean electrochemical device that combines hydrogen fuel with oxygen (from the air) to produce electricity. Key geographical revenue is derived from United States followed by Poland, Canada, and other countries.",
  "ticker_root": "BLDP",
  "homepage_url": "https://www.ballard.com",
  "total_employees": 492,
  "list_date": "1995-11-08",
  "branding": {
    "logo_url": "https://api.polygon.io/v1/reference/company-branding/YmFsbGFyZC5jb20/images/2025-04-04_logo.svg",
    "icon_url": "https://api.polygon.io/v1/reference/company-branding/YmFsbGFyZC5jb20/images/2025-04-04_icon.jpeg"
  },
  "share_class_shares_outstanding": 301475849,
  "weighted_shares_outstanding": 301475849,
  "round_lot": 100
}