{
  "ticker": "BLDR",
  "name": "Builders FirstSource, Inc.",
  "market": "stocks",
  "locale": "us",
  "primary_exchange": "XNYS",
  "type": "CS",
  "active": true,
  "currency_name": "usd",
  "cik": "0001316835",
  "composite_figi": "BBG000BKD3K9",
  "share_class_figi": "BBG001S9CFC7",
  "market_cap": 8084200280.16,
  "phone_number": "(214) 880-3500",
  "address": {
    "address1": "6031 CONNECTION DR., STE. 400",
    "city": "IRVING",
    "state": "TX",
    "postal_code": "75039"
  },
  "description": "Builders FirstSource Inc is a manufacturer and supplier of building materials. The company offers structural and related building products such as factory-built roof and floor trusses, wall panels and stairs, vinyl windows, custom millwork and trim, and engineered wood. The products can be designed for each home individually and are installed by Builders FirstSource. The company's construction-related services include professional installation, turn-key framing, and shell construction. Builders FirstSource's customers range from large production builders to small custom homebuilders.",
  "sic_code": "5211",
  "sic_description": "RETAIL-LUMBER & OTHER BUILDING MATERIALS DEALERS",
  "ticker_root": "BLDR",
  "homepage_url": "https://www.bldr.com",
  "total_employees": 28000,
  "list_date": "2005-06-22",
  "branding": {
    "logo_url": "https://api.polygon.io/v1/reference/company-branding/Ymxkci5jb20/images/2026-07-01_logo.png",
    "icon_url": "https://api.polygon.io/v1/reference/company-branding/Ymxkci5jb20/images/2026-07-01_icon.jpeg"
  },
  "share_class_shares_outstanding": 107559876,
  "weighted_shares_outstanding": 107559876,
  "round_lot": 100
}