{
  "ticker": "CRGY",
  "name": "Crescent Energy Company",
  "market": "stocks",
  "locale": "us",
  "primary_exchange": "XNYS",
  "type": "CS",
  "active": true,
  "currency_name": "usd",
  "cik": "0001866175",
  "composite_figi": "BBG013THLHZ4",
  "share_class_figi": "BBG013THLJ08",
  "market_cap": 3447826996.3199997,
  "phone_number": "713-332-7001",
  "address": {
    "address1": "600 TRAVIS STREET",
    "address2": "SUITE 7200",
    "city": "HOUSTON",
    "state": "TX",
    "postal_code": "77002"
  },
  "description": "Crescent Energy Co is an energy company committed to delivering value for shareholders through disciplined growth, acquisition ideas, and the consistent return of capital. Its long-life, balanced portfolio combines stable cash flows from low-decline production with deep, high-quality development inventory. The company operates in one reportable segment, which is the exploration and production of crude oil, natural gas, and NGLs.",
  "sic_code": "1311",
  "sic_description": "CRUDE PETROLEUM & NATURAL GAS",
  "ticker_root": "CRGY",
  "homepage_url": "https://www.crescentenergyco.com",
  "total_employees": 1066,
  "list_date": "2021-12-08",
  "branding": {
    "logo_url": "https://api.polygon.io/v1/reference/company-branding/Y3Jlc2NlbnRlbmVyZ3ljby5jb20/images/2025-04-04_logo.png",
    "icon_url": "https://api.polygon.io/v1/reference/company-branding/Y3Jlc2NlbnRlbmVyZ3ljby5jb20/images/2025-04-04_icon.jpeg"
  },
  "share_class_shares_outstanding": 330251628,
  "weighted_shares_outstanding": 330251628,
  "round_lot": 100
}