{
  "ticker": "DVN",
  "name": "Devon Energy Corporation",
  "market": "stocks",
  "locale": "us",
  "primary_exchange": "XNYS",
  "type": "CS",
  "active": true,
  "currency_name": "usd",
  "cik": "0001090012",
  "composite_figi": "BBG000BBVJZ8",
  "share_class_figi": "BBG001S63VG4",
  "market_cap": 49111904296.06,
  "phone_number": "(405) 552-3333",
  "address": {
    "address1": "333 W. SHERIDAN AVENUE",
    "city": "OKLAHOMA CITY",
    "state": "OK",
    "postal_code": "73102"
  },
  "description": "Devon Energy is an oil and gas producer with acreage in several top US shale plays. While roughly two-thirds of its production comes from the Permian Basin, it also holds a meaningful presence in the Anadarko, Eagle Ford, and Bakken basins. After the merger with Coterra, it will have a foothold in the gas-driven Appalachian Basin as well. At the end of 2025, Devon reported net proved reserves of 2.4 billion barrels of oil equivalent, up from 2.2 billion in 2024. Net production averaged roughly 840,000 barrels of oil equivalent per day in 2025 at a ratio of 73% oil and natural gas liquids and 27% natural gas.",
  "sic_code": "1311",
  "sic_description": "CRUDE PETROLEUM & NATURAL GAS",
  "ticker_root": "DVN",
  "homepage_url": "https://www.devonenergy.com",
  "total_employees": 2200,
  "list_date": "1988-09-30",
  "branding": {
    "logo_url": "https://api.polygon.io/v1/reference/company-branding/ZGV2b25lbmVyZ3kuY29t/images/2025-04-04_logo.svg",
    "icon_url": "https://api.polygon.io/v1/reference/company-branding/ZGV2b25lbmVyZ3kuY29t/images/2025-04-04_icon.jpeg"
  },
  "share_class_shares_outstanding": 1153403107,
  "weighted_shares_outstanding": 1153403107,
  "round_lot": 100
}