{
  "ticker": "FMX",
  "name": "FOMENTO ECONOMICO MEXICANO, S.A.B. DE C.V.",
  "market": "stocks",
  "locale": "us",
  "primary_exchange": "XNYS",
  "type": "ADRC",
  "active": true,
  "currency_name": "usd",
  "cik": "0001061736",
  "composite_figi": "BBG000BD33X2",
  "share_class_figi": "BBG001S5W9K8",
  "market_cap": 42775965122.08,
  "description": "Mexico-based Femsa is a beverage and retail conglomerate in Central and South America. The holding company owns controlling stakes in bottler Coca-Cola Femsa (47% economic stake, 56% voting rights), in addition to operating 100%-owned retail assets, including convenience stores under the Oxxo banner, drugstores, and gas stations. The firm divested its 15% stake in Heineken and its distribution business in 2023. Coca-Cola Femsa and the Oxxo chain made up over 70% of total company revenue and over 90% of profits in 2025.",
  "ticker_root": "FMX",
  "homepage_url": "https://www.femsa.com",
  "total_employees": 368776,
  "list_date": "1998-05-11",
  "branding": {
    "logo_url": "https://api.polygon.io/v1/reference/company-branding/ZmVtc2EuY29t/images/2025-04-04_logo.png",
    "icon_url": "https://api.polygon.io/v1/reference/company-branding/ZmVtc2EuY29t/images/2025-04-04_icon.jpeg"
  },
  "share_class_shares_outstanding": 202267251,
  "weighted_shares_outstanding": 340681468,
  "round_lot": 100
}