{
  "ticker": "GBCI",
  "name": "Glacier Bancorp Inc",
  "market": "stocks",
  "locale": "us",
  "primary_exchange": "XNYS",
  "type": "CS",
  "active": true,
  "currency_name": "usd",
  "cik": "0000868671",
  "composite_figi": "BBG000C3KB84",
  "share_class_figi": "BBG001S6HGM5",
  "market_cap": 6266368790.099999,
  "phone_number": "406-751-7708",
  "address": {
    "address1": "49 COMMONS LOOP",
    "city": "KALISPELL",
    "state": "MT",
    "postal_code": "59901"
  },
  "description": "Glacier Bancorp Inc is a regional bank holding company providing commercial banking services through its wholly owned bank subsidiary, Glacier Bank. The group provides a full range of banking services to individuals, small to medium-sized businesses, community organizations, and public entities from several locations in Montana, Idaho, Utah, Washington, Wyoming, Colorado, Arizona, Nevada, and Texas. It offers various banking products and services, including: retail banking, business banking, real estate, commercial, agriculture, and consumer loans; and mortgage origination and loan servicing services, among others.",
  "sic_code": "6022",
  "sic_description": "STATE COMMERCIAL BANKS",
  "ticker_root": "GBCI",
  "homepage_url": "https://www.glacierbancorp.com",
  "total_employees": 4139,
  "list_date": "1984-03-22",
  "branding": {
    "logo_url": "https://api.polygon.io/v1/reference/company-branding/Z2xhY2llcmJhbmNvcnAuY29t/images/2025-04-04_logo.svg"
  },
  "share_class_shares_outstanding": 130142654,
  "weighted_shares_outstanding": 130142654,
  "round_lot": 100
}