{
  "ticker": "GEHC",
  "name": "GE HealthCare Technologies Inc. Common Stock",
  "market": "stocks",
  "locale": "us",
  "primary_exchange": "XNAS",
  "type": "CS",
  "active": true,
  "currency_name": "usd",
  "cik": "0001932393",
  "composite_figi": "BBG01BFR8YV1",
  "share_class_figi": "BBG01BFR8YW0",
  "market_cap": 27816632713.899998,
  "phone_number": "833-735-1139",
  "address": {
    "address1": "500 WEST MONROE STREET",
    "city": "CHICAGO",
    "state": "IL",
    "postal_code": "60661"
  },
  "description": "GE HealthCare Technologies is a leading medical technology firm with leading market share in imaging and ultrasound equipment. The company reports four major segments: imaging (45% of revenue), advanced visualization solutions (26%), patient care solutions (15%), and pharmaceutical diagnostics (14%). The company's sales are geographically diverse, with the United States, EMEA, China, and the rest of the world accounting for 46%, 26%, 11%, and 17%, respectively. We estimate approximately half of its revenue is recurring, which consists of servicing (about one-third of revenue), pharmaceutical diagnostics (about 10%-15%), and digital solutions (just over 5%).",
  "sic_code": "3844",
  "sic_description": "X-RAY APPARATUS & TUBES & RELATED IRRADIATION APPARATUS",
  "ticker_root": "GEHC",
  "homepage_url": "https://www.gehealthcare.com",
  "total_employees": 54000,
  "list_date": "2022-12-15",
  "branding": {
    "logo_url": "https://api.polygon.io/v1/reference/company-branding/Z2VoZWFsdGhjYXJlLmNvbQ/images/2025-04-04_logo.svg",
    "icon_url": "https://api.polygon.io/v1/reference/company-branding/Z2VoZWFsdGhjYXJlLmNvbQ/images/2025-04-04_icon.jpeg"
  },
  "share_class_shares_outstanding": 454891786,
  "weighted_shares_outstanding": 454891786,
  "round_lot": 100
}