{
  "ticker": "HLT",
  "name": "Hilton Worldwide Holdings Inc.",
  "market": "stocks",
  "locale": "us",
  "primary_exchange": "XNYS",
  "type": "CS",
  "active": true,
  "currency_name": "usd",
  "cik": "0001585689",
  "composite_figi": "BBG0058KMH30",
  "share_class_figi": "BBG0058KMH49",
  "market_cap": 79517576339.6,
  "phone_number": "703-883-1000",
  "address": {
    "address1": "7930 JONES BRANCH DRIVE, SUITE 1100",
    "city": "MCLEAN",
    "state": "VA",
    "postal_code": "22102"
  },
  "description": "Hilton Worldwide Holdings operates 1.36 million rooms across its 27 brands, serving the premium economy through luxury segments. Hampton and Hilton are the two largest brands, representing 27% and 18%, respectively, of the company's total rooms, as of Dec. 31, 2025. Recent brands launched over the past few years include Home2, Curio, Canopy, Spark, Tru, Tempo, LivSmart, and Outset. Additionally, there is a partnership with Small Luxury Hotels of the World and acquisitions of NoMad and Graduate Hotels. Managed and franchised hotels represent the vast majority of adjusted EBITDA, predominantly from the Americas.",
  "sic_code": "7011",
  "sic_description": "HOTELS & MOTELS",
  "ticker_root": "HLT",
  "homepage_url": "https://www.hilton.com",
  "total_employees": 182000,
  "list_date": "2013-12-12",
  "branding": {
    "logo_url": "https://api.polygon.io/v1/reference/company-branding/aGlsdG9uLmNvbQ/images/2025-04-04_logo.svg",
    "icon_url": "https://api.polygon.io/v1/reference/company-branding/aGlsdG9uLmNvbQ/images/2025-04-04_icon.jpeg"
  },
  "share_class_shares_outstanding": 227648372,
  "weighted_shares_outstanding": 227648372,
  "round_lot": 40
}