{
  "ticker": "HSBC",
  "name": "HSBC Holdings PLC",
  "market": "stocks",
  "locale": "us",
  "primary_exchange": "XNYS",
  "type": "ADRC",
  "active": true,
  "currency_name": "usd",
  "cik": "0001089113",
  "composite_figi": "BBG000C1K7N0",
  "share_class_figi": "BBG001SCZVC0",
  "market_cap": 326604798232.23004,
  "description": "Established in 1865 in Hong Kong, London-based HSBC is one of the largest banks in the world, with assets of USD 3 trillion and over 40 million customers worldwide. It operates in more than 50 countries with over 200,000 full-time staff. Hong Kong and the United Kingdom are its two largest markets. The bank offers retail, commercial and institutional banking, global banking and markets, wealth management, and private banking.",
  "ticker_root": "HSBC",
  "homepage_url": "https://www.hsbc.com",
  "total_employees": 209000,
  "list_date": "1995-05-11",
  "branding": {
    "logo_url": "https://api.polygon.io/v1/reference/company-branding/aHNiYy5jb20/images/2025-04-04_logo.svg",
    "icon_url": "https://api.polygon.io/v1/reference/company-branding/aHNiYy5jb20/images/2025-04-04_icon.png"
  },
  "share_class_shares_outstanding": 3436712768,
  "weighted_shares_outstanding": 3429641901,
  "round_lot": 100
}