{
  "ticker": "LUV",
  "name": "Southwest Airlines Co.",
  "market": "stocks",
  "locale": "us",
  "primary_exchange": "XNYS",
  "type": "CS",
  "active": true,
  "currency_name": "usd",
  "cik": "0000092380",
  "composite_figi": "BBG000BNJHS8",
  "share_class_figi": "BBG001S5SXC9",
  "market_cap": 22806181448.579998,
  "phone_number": "(214) 792-4000",
  "address": {
    "address1": "2702 LOVE FIELD DR",
    "address2": "P O BOX 36611",
    "city": "DALLAS",
    "state": "TX",
    "postal_code": "75235"
  },
  "description": "Southwest Airlines is the largest domestic air carrier in the United States by passengers boarded. Southwest operates nearly 800 aircraft in an all-Boeing 737 fleet. Despite offering some longer routes and a few perks for business travelers, the airline predominantly specializes in short-haul, leisure flights operated with a simple cabin configuration in a point-to-point network. In early 2026, Southwest modified its cabins to offer some rows with extra legroom, its ticketing process and merchandising to offer assigned seats, and more fare categories to include a basic economy class that appears for the first time in travel aggregators' search results and more directly competes with other airlines' offerings.",
  "sic_code": "4512",
  "sic_description": "AIR TRANSPORTATION, SCHEDULED",
  "ticker_root": "LUV",
  "homepage_url": "https://www.southwest.com",
  "total_employees": 73401,
  "list_date": "1973-01-02",
  "branding": {
    "logo_url": "https://api.polygon.io/v1/reference/company-branding/c291dGh3ZXN0LmNvbQ/images/2025-04-04_logo.svg",
    "icon_url": "https://api.polygon.io/v1/reference/company-branding/c291dGh3ZXN0LmNvbQ/images/2025-04-04_icon.jpeg"
  },
  "share_class_shares_outstanding": 488773713,
  "weighted_shares_outstanding": 488773713,
  "round_lot": 100
}