{
  "ticker": "MSCI",
  "name": "MSCI, Inc.",
  "market": "stocks",
  "locale": "us",
  "primary_exchange": "XNYS",
  "type": "CS",
  "active": true,
  "currency_name": "usd",
  "cik": "0001408198",
  "composite_figi": "BBG000RTDY25",
  "share_class_figi": "BBG001SV8B05",
  "market_cap": 43453592000.0,
  "phone_number": "212-804-3990",
  "address": {
    "address1": "7 WORLD TRADE CENTER",
    "address2": "250 GREENWICH STREET 49TH FLOOR",
    "city": "NEW YORK",
    "state": "NY",
    "postal_code": "10007"
  },
  "description": "MSCI has described its mission as enabling investors to build better portfolios for a better world. MSCI's largest and most profitable segment is its index segment, where it provides benchmarking to asset managers and asset owners. MSCI boasts over $18 trillion (as of December 2025) in benchmarked assets, including over $2.3 trillion in ETF assets linked to MSCI indexes. The MSCI analytics segment provides portfolio management and risk management analytics software to asset managers and asset owners. In its sustainability and climate segment, MSCI provides ESG data to the investment industry. In private assets, MSCI provides real restate reporting, market data, benchmarking, and analytics to investors and real estate managers.",
  "sic_code": "7389",
  "sic_description": "SERVICES-BUSINESS SERVICES, NEC",
  "ticker_root": "MSCI",
  "homepage_url": "https://www.msci.com",
  "total_employees": 6319,
  "list_date": "2007-11-15",
  "branding": {
    "logo_url": "https://api.polygon.io/v1/reference/company-branding/bXNjaS5jb20/images/2025-04-04_logo.svg",
    "icon_url": "https://api.polygon.io/v1/reference/company-branding/bXNjaS5jb20/images/2025-04-04_icon.jpeg"
  },
  "weighted_shares_outstanding": 72800000,
  "round_lot": 40
}