{
  "ticker": "SBAC",
  "name": "SBA Communications Corp",
  "market": "stocks",
  "locale": "us",
  "primary_exchange": "XNAS",
  "type": "CS",
  "active": true,
  "currency_name": "usd",
  "cik": "0001034054",
  "composite_figi": "BBG000D2M0Z7",
  "share_class_figi": "BBG001SCWNN9",
  "market_cap": 20318492166.69,
  "phone_number": "(561) 226-9345",
  "address": {
    "address1": "8051 CONGRESS AVENUE",
    "city": "BOCA RATON",
    "state": "FL",
    "postal_code": "33487"
  },
  "description": "SBA Communications owns a portfolio of about 46,000 wireless towers throughout North America, South America, and Africa. It leases space on its towers to wireless service providers, who install equipment to support their wireless networks. The company has a very concentrated customer base, with most revenue in each market generated by the top three or four mobile carriers. It owns more than 17,000 towers in the US, which account for about 70% of leasing revenue. Internationally, SBA's largest markets are Brazil and Guatemala, where it owns roughly 12,000 and 5,000 towers, respectively. SBA operates as a real estate investment trust.",
  "sic_code": "6798",
  "sic_description": "REAL ESTATE INVESTMENT TRUSTS",
  "ticker_root": "SBAC",
  "homepage_url": "https://www.sbasite.com",
  "total_employees": 1844,
  "list_date": "1999-06-16",
  "branding": {
    "logo_url": "https://api.polygon.io/v1/reference/company-branding/c2Jhc2l0ZS5jb20/images/2025-04-04_logo.svg",
    "icon_url": "https://api.polygon.io/v1/reference/company-branding/c2Jhc2l0ZS5jb20/images/2025-04-04_icon.png"
  },
  "share_class_shares_outstanding": 106063017,
  "weighted_shares_outstanding": 106063017,
  "round_lot": 100
}