{
  "ticker": "SLAB",
  "name": "Silicon Laboratories Inc",
  "market": "stocks",
  "locale": "us",
  "primary_exchange": "XNAS",
  "type": "CS",
  "active": true,
  "currency_name": "usd",
  "cik": "0001038074",
  "composite_figi": "BBG000BB99S3",
  "share_class_figi": "BBG001S5W492",
  "market_cap": 7210156326.030001,
  "phone_number": "(512) 416-8500",
  "address": {
    "address1": "400 W CESAR CHAVEZ",
    "city": "AUSTIN",
    "state": "TX",
    "postal_code": "78701"
  },
  "description": "Silicon Laboratories Inc Inc is a provider of secure, intelligent wireless technology for a more connected world. The company's integrated hardware and software platform, intuitive development tools, industry ecosystem, and robust support help customers build industrial, commercial, home, and life applications. Company make it easy for developers to solve complex wireless challenges throughout the product lifecycle and get to market quickly with solutions that transform industries, grow economies, and improve lives. Company operates in USA, China, Taiwan and Rest of World, with maximum revenue from rest of the world.",
  "sic_code": "3674",
  "sic_description": "SEMICONDUCTORS & RELATED DEVICES",
  "ticker_root": "SLAB",
  "homepage_url": "https://www.silabs.com",
  "total_employees": 1930,
  "list_date": "2000-03-24",
  "branding": {
    "logo_url": "https://api.polygon.io/v1/reference/company-branding/c2lsYWJzLmNvbQ/images/2025-04-04_logo.svg",
    "icon_url": "https://api.polygon.io/v1/reference/company-branding/c2lsYWJzLmNvbQ/images/2025-04-04_icon.png"
  },
  "share_class_shares_outstanding": 32981823,
  "weighted_shares_outstanding": 32981823,
  "round_lot": 100
}