{
  "ticker": "TIMB",
  "name": "TIM S.A. American Depositary Shares (Each representing 5 Common Shares)",
  "market": "stocks",
  "locale": "us",
  "primary_exchange": "XNYS",
  "type": "ADRC",
  "active": true,
  "currency_name": "usd",
  "cik": "0001826168",
  "composite_figi": "BBG00XS5M9S1",
  "share_class_figi": "BBG00XS5MBP9",
  "market_cap": 10027629607.359999,
  "description": "TIM, which is 67%-owned by Telecom Italia, is the third-largest wireless carrier in Brazil, with 62 million subscribers, equal to about 23% of the market. The firm owns 49% of I-Systems, an infrastructure partnership that is expanding its network footprint across Brazil. I-Systems can provide broadband service to about 8 million locations, including 6.5 million with fiber, equal to 10%-15% of the country. TIM leases capacity on the venture's network to serve retail broadband customers under the UltraFibra brand, but it has agreed to buy out its joint venture partner in 2026 and will take full ownership of these assets. TIM also resells fiber network access from other providers.",
  "ticker_root": "TIMB",
  "homepage_url": "https://www.tim.com.br",
  "total_employees": 8706,
  "list_date": "1998-11-16",
  "share_class_shares_outstanding": 478425178,
  "weighted_shares_outstanding": 477733664,
  "round_lot": 100
}