{
  "ticker": "WSO",
  "name": "Watsco, Inc.",
  "market": "stocks",
  "locale": "us",
  "primary_exchange": "XNYS",
  "type": "CS",
  "active": true,
  "currency_name": "usd",
  "cik": "0000105016",
  "composite_figi": "BBG000DJN7L9",
  "share_class_figi": "BBG001S82CQ2",
  "market_cap": 15831950297.64,
  "phone_number": "305-714-4100",
  "address": {
    "address1": "2665 S BAYSHORE DR",
    "address2": "STE 901",
    "city": "COCONUT GROVE",
    "state": "FL",
    "postal_code": "33133"
  },
  "description": "Watsco is the largest HVAC and refrigeration products distributor in North America with approximately 13% market share. The company primarily operates in the United States (90% of revenue) with significant exposure in the Sunbelt states. Watsco also has operations in Canada, Latin America, and the Caribbean. The company's customer base comprises more than 120,000 dealers and contractors serving the replacement and new-construction HVAC/R markets for residential and light-commercial applications. As much as 20% of residential HVAC units are distributed through Watsco in any given year. Revenue is approximately 75%-80% residential HVAC and 20%-25% commercial, with relatively small exposure to more complex \"applied\" solutions.",
  "sic_code": "5070",
  "sic_description": "WHOLESALE-HARDWARE & PLUMBING & HEATING EQUIPMENT & SUPPLIES",
  "ticker_root": "WSO",
  "homepage_url": "https://www.watsco.com",
  "total_employees": 7050,
  "list_date": "1984-06-07",
  "branding": {
    "logo_url": "https://api.polygon.io/v1/reference/company-branding/d2F0c2NvLmNvbQ/images/2025-04-04_logo.png"
  },
  "share_class_shares_outstanding": 35016653,
  "weighted_shares_outstanding": 41188278,
  "round_lot": 40
}