{
  "start_date": "2025-01-01",
  "end_date": "2025-12-31",
  "filing_date": "2026-02-27",
  "acceptance_datetime": "2026-02-27T20:58:24Z",
  "timeframe": "annual",
  "fiscal_period": "FY",
  "fiscal_year": "2025",
  "cik": "0002042694",
  "sic": "2080",
  "tickers": [
    "PRMB"
  ],
  "company_name": "Primo Brands Corp",
  "source_filing_url": "https://api.polygon.io/v1/reference/sec/filings/0001628280-26-012779",
  "source_filing_file_url": "http://api.polygon.io/v1/reference/sec/filings/0001628280-26-012779/files/prmb-20251231_htm.xml",
  "financials": {
    "balance_sheet": {
      "assets": {
        "value": 10602800000.0,
        "unit": "USD",
        "label": "Assets",
        "order": 100
      },
      "current_liabilities": {
        "value": 1282700000.0,
        "unit": "USD",
        "label": "Current Liabilities",
        "order": 700
      },
      "noncurrent_liabilities": {
        "value": 6327500000.0,
        "unit": "USD",
        "label": "Noncurrent Liabilities",
        "order": 800
      },
      "wages": {
        "value": 69300000.0,
        "unit": "USD",
        "label": "Wages",
        "order": 730
      },
      "other_current_liabilities": {
        "value": 694500000.0,
        "unit": "USD",
        "label": "Other Current Liabilities",
        "order": 740
      },
      "liabilities_and_equity": {
        "value": 10602800000.0,
        "unit": "USD",
        "label": "Liabilities And Equity",
        "order": 1900
      },
      "equity_attributable_to_noncontrolling_interest": {
        "value": 0,
        "unit": "USD",
        "label": "Equity Attributable To Noncontrolling Interest",
        "order": 1500
      },
      "accounts_payable": {
        "value": 518900000.0,
        "unit": "USD",
        "label": "Accounts Payable",
        "order": 710
      },
      "current_assets": {
        "value": 1217800000.0,
        "unit": "USD",
        "label": "Current Assets",
        "order": 200
      },
      "equity": {
        "value": 2992600000.0,
        "unit": "USD",
        "label": "Equity",
        "order": 1400
      },
      "equity_attributable_to_parent": {
        "value": 2992600000.0,
        "unit": "USD",
        "label": "Equity Attributable To Parent",
        "order": 1600
      },
      "liabilities": {
        "value": 7610200000.0,
        "unit": "USD",
        "label": "Liabilities",
        "order": 600
      },
      "inventory": {
        "value": 223500000.0,
        "unit": "USD",
        "label": "Inventory",
        "order": 230
      },
      "other_noncurrent_assets": {
        "value": 6392300000.0,
        "unit": "USD",
        "label": "Other Non-current Assets",
        "order": 350
      },
      "other_noncurrent_liabilities": {
        "value": 1249200000.0,
        "unit": "USD",
        "label": "Other Non-current Liabilities",
        "order": 820
      },
      "noncurrent_assets": {
        "value": 9385000000.0,
        "unit": "USD",
        "label": "Noncurrent Assets",
        "order": 300
      },
      "long_term_debt": {
        "value": 5078300000.0,
        "unit": "USD",
        "label": "Long-term Debt",
        "order": 810
      },
      "intangible_assets": {
        "value": 2992700000.0,
        "unit": "USD",
        "label": "Intangible Assets",
        "order": 330
      },
      "other_current_assets": {
        "value": 994300000.0,
        "unit": "USD",
        "label": "Other Current Assets",
        "order": 250
      }
    },
    "income_statement": {
      "diluted_earnings_per_share": {
        "value": 0.16,
        "unit": "USD / shares",
        "label": "Diluted Earnings Per Share",
        "order": 4300
      },
      "cost_of_revenue": {
        "value": 4643800000.0,
        "unit": "USD",
        "label": "Cost Of Revenue",
        "order": 300
      },
      "basic_earnings_per_share": {
        "value": 0.16,
        "unit": "USD / shares",
        "label": "Basic Earnings Per Share",
        "order": 4200
      },
      "other_operating_expenses": {
        "value": 199400000.0,
        "unit": "USD",
        "label": "Other Operating Expenses",
        "order": 1040
      },
      "net_income_loss": {
        "value": 60100000.0,
        "unit": "USD",
        "label": "Net Income/Loss",
        "order": 3200
      },
      "income_tax_expense_benefit_deferred": {
        "value": -46200000.0,
        "unit": "USD",
        "label": "Income Tax Expense/Benefit, Deferred",
        "order": 2400
      },
      "revenues": {
        "value": 6664000000.0,
        "unit": "USD",
        "label": "Revenues",
        "order": 100
      },
      "net_income_loss_attributable_to_parent": {
        "value": 60100000.0,
        "unit": "USD",
        "label": "Net Income/Loss Attributable To Parent",
        "order": 3500
      },
      "income_tax_expense_benefit": {
        "value": 64600000.0,
        "unit": "USD",
        "label": "Income Tax Expense/Benefit",
        "order": 2200
      },
      "costs_and_expenses": {
        "value": 6519000000.0,
        "unit": "USD",
        "label": "Costs And Expenses",
        "order": 600
      },
      "diluted_average_shares": {
        "value": 374869000.0,
        "unit": "shares",
        "label": "Diluted Average Shares",
        "order": 4500
      },
      "income_loss_from_continuing_operations_after_tax": {
        "value": 80400000.0,
        "unit": "USD",
        "label": "Income/Loss From Continuing Operations After Tax",
        "order": 1400
      },
      "preferred_stock_dividends_and_other_adjustments": {
        "value": 0,
        "unit": "USD",
        "label": "Preferred Stock Dividends And Other Adjustments",
        "order": 3900
      },
      "benefits_costs_expenses": {
        "value": 6519000000.0,
        "unit": "USD",
        "label": "Benefits Costs and Expenses",
        "order": 200
      },
      "income_loss_from_continuing_operations_before_tax": {
        "value": 145000000.0,
        "unit": "USD",
        "label": "Income/Loss From Continuing Operations Before Tax",
        "order": 1500
      },
      "income_loss_from_discontinued_operations_net_of_tax": {
        "value": -20300000.0,
        "unit": "USD",
        "label": "Income/Loss From Discontinued Operations Net Of Tax",
        "order": 1600
      },
      "income_tax_expense_benefit_current": {
        "value": 110800000.0,
        "unit": "USD",
        "label": "Income Tax Expense/Benefit, Current",
        "order": 2300
      },
      "operating_income_loss": {
        "value": 430400000.0,
        "unit": "USD",
        "label": "Operating Income/Loss",
        "order": 1100
      },
      "selling_general_and_administrative_expenses": {
        "value": 1390400000.0,
        "unit": "USD",
        "label": "Selling, General, and Administrative Expenses",
        "order": 1010
      },
      "basic_average_shares": {
        "value": 373512000.0,
        "unit": "shares",
        "label": "Basic Average Shares",
        "order": 4400
      },
      "participating_securities_distributed_and_undistributed_earnings_loss_basic": {
        "value": 0,
        "unit": "USD",
        "label": "Participating Securities, Distributed And Undistributed Earnings/Loss, Basic",
        "order": 3800
      },
      "net_income_loss_available_to_common_stockholders_basic": {
        "value": 60100000.0,
        "unit": "USD",
        "label": "Net Income/Loss Available To Common Stockholders, Basic",
        "order": 3700
      },
      "gross_profit": {
        "value": 2020200000.0,
        "unit": "USD",
        "label": "Gross Profit",
        "order": 800
      },
      "net_income_loss_attributable_to_noncontrolling_interest": {
        "value": 0,
        "unit": "USD",
        "label": "Net Income/Loss Attributable To Noncontrolling Interest",
        "order": 3300
      },
      "operating_expenses": {
        "value": 1589800000.0,
        "unit": "USD",
        "label": "Operating Expenses",
        "order": 1000
      }
    },
    "cash_flow_statement": {
      "net_cash_flow_discontinued": {
        "value": 43700000.0,
        "unit": "USD",
        "label": "Net Cash Flow, Discontinued",
        "order": 1300
      },
      "net_cash_flow": {
        "value": -245900000.0,
        "unit": "USD",
        "label": "Net Cash Flow",
        "order": 1100
      },
      "net_cash_flow_from_financing_activities_discontinued": {
        "value": -2200000.0,
        "unit": "USD",
        "label": "Net Cash Flow From Financing Activities, Discontinued",
        "order": 900
      },
      "net_cash_flow_continuing": {
        "value": -289600000.0,
        "unit": "USD",
        "label": "Net Cash Flow, Continuing",
        "order": 1200
      },
      "net_cash_flow_from_financing_activities_continuing": {
        "value": -632000000.0,
        "unit": "USD",
        "label": "Net Cash Flow From Financing Activities, Continuing",
        "order": 800
      },
      "net_cash_flow_from_investing_activities_discontinued": {
        "value": 38800000.0,
        "unit": "USD",
        "label": "Net Cash Flow From Investing Activities, Discontinued",
        "order": 600
      },
      "net_cash_flow_from_operating_activities": {
        "value": 687400000.0,
        "unit": "USD",
        "label": "Net Cash Flow From Operating Activities",
        "order": 100
      },
      "net_cash_flow_from_operating_activities_discontinued": {
        "value": 7100000.0,
        "unit": "USD",
        "label": "Net Cash Flow From Operating Activities, Discontinued",
        "order": 300
      },
      "net_cash_flow_from_investing_activities_continuing": {
        "value": -337900000.0,
        "unit": "USD",
        "label": "Net Cash Flow From Investing Activities, Continuing",
        "order": 500
      },
      "net_cash_flow_from_operating_activities_continuing": {
        "value": 680300000.0,
        "unit": "USD",
        "label": "Net Cash Flow From Operating Activities, Continuing",
        "order": 200
      },
      "net_cash_flow_from_financing_activities": {
        "value": -634200000.0,
        "unit": "USD",
        "label": "Net Cash Flow From Financing Activities",
        "order": 700
      },
      "net_cash_flow_from_investing_activities": {
        "value": -299100000.0,
        "unit": "USD",
        "label": "Net Cash Flow From Investing Activities",
        "order": 400
      }
    },
    "comprehensive_income": {
      "other_comprehensive_income_loss_attributable_to_parent": {
        "value": 3300000.0,
        "unit": "USD",
        "label": "Other Comprehensive Income/Loss Attributable To Parent",
        "order": 600
      },
      "comprehensive_income_loss_attributable_to_parent": {
        "value": 63400000.0,
        "unit": "USD",
        "label": "Comprehensive Income/Loss Attributable To Parent",
        "order": 300
      },
      "comprehensive_income_loss_attributable_to_noncontrolling_interest": {
        "value": 0,
        "unit": "USD",
        "label": "Comprehensive Income/Loss Attributable To Noncontrolling Interest",
        "order": 200
      },
      "other_comprehensive_income_loss": {
        "value": 63400000.0,
        "unit": "USD",
        "label": "Other Comprehensive Income/Loss",
        "order": 400
      },
      "comprehensive_income_loss": {
        "value": 63400000.0,
        "unit": "USD",
        "label": "Comprehensive Income/Loss",
        "order": 100
      }
    }
  }
}