{
  "start_date": "2024-06-30",
  "end_date": "2025-06-28",
  "filing_date": "2025-08-14",
  "acceptance_datetime": "2025-08-14T10:50:57Z",
  "timeframe": "annual",
  "fiscal_period": "FY",
  "fiscal_year": "2025",
  "cik": "0001116132",
  "sic": "3100",
  "tickers": [
    "TPR"
  ],
  "company_name": "TAPESTRY, INC.",
  "source_filing_url": "https://api.polygon.io/v1/reference/sec/filings/0001116132-25-000019",
  "source_filing_file_url": "http://api.polygon.io/v1/reference/sec/filings/0001116132-25-000019/files/tpr-20250628_htm.xml",
  "financials": {
    "comprehensive_income": {
      "comprehensive_income_loss": {
        "value": 67900000.0,
        "unit": "USD",
        "label": "Comprehensive Income/Loss",
        "order": 100
      },
      "other_comprehensive_income_loss_attributable_to_parent": {
        "value": -115300000.0,
        "unit": "USD",
        "label": "Other Comprehensive Income/Loss Attributable To Parent",
        "order": 600
      },
      "comprehensive_income_loss_attributable_to_parent": {
        "value": 67900000.0,
        "unit": "USD",
        "label": "Comprehensive Income/Loss Attributable To Parent",
        "order": 300
      },
      "comprehensive_income_loss_attributable_to_noncontrolling_interest": {
        "value": 0,
        "unit": "USD",
        "label": "Comprehensive Income/Loss Attributable To Noncontrolling Interest",
        "order": 200
      },
      "other_comprehensive_income_loss": {
        "value": 67900000.0,
        "unit": "USD",
        "label": "Other Comprehensive Income/Loss",
        "order": 400
      }
    },
    "income_statement": {
      "net_income_loss": {
        "value": 183200000.0,
        "unit": "USD",
        "label": "Net Income/Loss",
        "order": 3200
      },
      "diluted_earnings_per_share": {
        "value": 0.82,
        "unit": "USD / shares",
        "label": "Diluted Earnings Per Share",
        "order": 4300
      },
      "preferred_stock_dividends_and_other_adjustments": {
        "value": 0,
        "unit": "USD",
        "label": "Preferred Stock Dividends And Other Adjustments",
        "order": 3900
      },
      "gross_profit": {
        "value": 5288900000.0,
        "unit": "USD",
        "label": "Gross Profit",
        "order": 800
      },
      "income_tax_expense_benefit_current": {
        "value": 172700000.0,
        "unit": "USD",
        "label": "Income Tax Expense/Benefit, Current",
        "order": 2300
      },
      "income_loss_from_continuing_operations_after_tax": {
        "value": 183200000.0,
        "unit": "USD",
        "label": "Income/Loss From Continuing Operations After Tax",
        "order": 1400
      },
      "basic_earnings_per_share": {
        "value": 0.84,
        "unit": "USD / shares",
        "label": "Basic Earnings Per Share",
        "order": 4200
      },
      "revenues": {
        "value": 7010700000.0,
        "unit": "USD",
        "label": "Revenues",
        "order": 100
      },
      "other_operating_expenses": {
        "value": 687400000.0,
        "unit": "USD",
        "label": "Other Operating Expenses",
        "order": 1040
      },
      "basic_average_shares": {
        "value": 216800000.0,
        "unit": "shares",
        "label": "Basic Average Shares",
        "order": 4400
      },
      "operating_expenses": {
        "value": 4873900000.0,
        "unit": "USD",
        "label": "Operating Expenses",
        "order": 1000
      },
      "provision_for_loan_lease_and_other_losses": {
        "value": 0,
        "unit": "USD",
        "label": "Provision For Loan, Lease, And Other Losses",
        "order": 4000
      },
      "interest_income_expense_after_provision_for_losses": {
        "value": -85400000.0,
        "unit": "USD",
        "label": "Interest Income/Expense After Provision For Losses",
        "order": 2800
      },
      "depreciation_and_amortization": {
        "value": 167400000.0,
        "unit": "USD",
        "label": "Depreciation and Amortization",
        "order": 1020
      },
      "net_income_loss_available_to_common_stockholders_basic": {
        "value": 183200000.0,
        "unit": "USD",
        "label": "Net Income/Loss Available To Common Stockholders, Basic",
        "order": 3700
      },
      "net_income_loss_attributable_to_parent": {
        "value": 183200000.0,
        "unit": "USD",
        "label": "Net Income/Loss Attributable To Parent",
        "order": 3500
      },
      "cost_of_revenue": {
        "value": 1721800000.0,
        "unit": "USD",
        "label": "Cost Of Revenue",
        "order": 300
      },
      "income_loss_from_continuing_operations_before_tax": {
        "value": 216100000.0,
        "unit": "USD",
        "label": "Income/Loss From Continuing Operations Before Tax",
        "order": 1500
      },
      "income_tax_expense_benefit": {
        "value": 32900000.0,
        "unit": "USD",
        "label": "Income Tax Expense/Benefit",
        "order": 2200
      },
      "operating_income_loss": {
        "value": 415000000.0,
        "unit": "USD",
        "label": "Operating Income/Loss",
        "order": 1100
      },
      "income_tax_expense_benefit_deferred": {
        "value": -139800000.0,
        "unit": "USD",
        "label": "Income Tax Expense/Benefit, Deferred",
        "order": 2400
      },
      "selling_general_and_administrative_expenses": {
        "value": 4019100000.0,
        "unit": "USD",
        "label": "Selling, General, and Administrative Expenses",
        "order": 1010
      },
      "diluted_average_shares": {
        "value": 222500000.0,
        "unit": "shares",
        "label": "Diluted Average Shares",
        "order": 4500
      },
      "participating_securities_distributed_and_undistributed_earnings_loss_basic": {
        "value": 0,
        "unit": "USD",
        "label": "Participating Securities, Distributed And Undistributed Earnings/Loss, Basic",
        "order": 3800
      },
      "net_income_loss_attributable_to_noncontrolling_interest": {
        "value": 0,
        "unit": "USD",
        "label": "Net Income/Loss Attributable To Noncontrolling Interest",
        "order": 3300
      },
      "interest_income_expense_operating_net": {
        "value": -85400000.0,
        "unit": "USD",
        "label": "Interest Income/Expense Operating, Net",
        "order": 2900
      },
      "costs_and_expenses": {
        "value": 6794600000.0,
        "unit": "USD",
        "label": "Costs And Expenses",
        "order": 600
      },
      "benefits_costs_expenses": {
        "value": 6794600000.0,
        "unit": "USD",
        "label": "Benefits Costs and Expenses",
        "order": 200
      }
    },
    "cash_flow_statement": {
      "net_cash_flow_from_operating_activities": {
        "value": 1216600000.0,
        "unit": "USD",
        "label": "Net Cash Flow From Operating Activities",
        "order": 100
      },
      "net_cash_flow_from_investing_activities_continuing": {
        "value": 914000000.0,
        "unit": "USD",
        "label": "Net Cash Flow From Investing Activities, Continuing",
        "order": 500
      },
      "exchange_gains_losses": {
        "value": 26300000.0,
        "unit": "USD",
        "label": "Exchange Gains/Losses",
        "order": 1000
      },
      "net_cash_flow": {
        "value": -5018300000.0,
        "unit": "USD",
        "label": "Net Cash Flow",
        "order": 1100
      },
      "net_cash_flow_continuing": {
        "value": -5044600000.0,
        "unit": "USD",
        "label": "Net Cash Flow, Continuing",
        "order": 1200
      },
      "net_cash_flow_from_operating_activities_continuing": {
        "value": 1216600000.0,
        "unit": "USD",
        "label": "Net Cash Flow From Operating Activities, Continuing",
        "order": 200
      },
      "net_cash_flow_from_financing_activities": {
        "value": -7175200000.0,
        "unit": "USD",
        "label": "Net Cash Flow From Financing Activities",
        "order": 700
      },
      "net_cash_flow_from_financing_activities_continuing": {
        "value": -7175200000.0,
        "unit": "USD",
        "label": "Net Cash Flow From Financing Activities, Continuing",
        "order": 800
      },
      "net_cash_flow_from_investing_activities": {
        "value": 914000000.0,
        "unit": "USD",
        "label": "Net Cash Flow From Investing Activities",
        "order": 400
      }
    },
    "balance_sheet": {
      "other_current_liabilities": {
        "value": 876400000.0,
        "unit": "USD",
        "label": "Other Current Liabilities",
        "order": 740
      },
      "equity": {
        "value": 857800000.0,
        "unit": "USD",
        "label": "Equity",
        "order": 1400
      },
      "prepaid_expenses": {
        "value": 133800000.0,
        "unit": "USD",
        "label": "Prepaid Expenses",
        "order": 240
      },
      "equity_attributable_to_noncontrolling_interest": {
        "value": 0,
        "unit": "USD",
        "label": "Equity Attributable To Noncontrolling Interest",
        "order": 1500
      },
      "equity_attributable_to_parent": {
        "value": 857800000.0,
        "unit": "USD",
        "label": "Equity Attributable To Parent",
        "order": 1600
      },
      "long_term_debt": {
        "value": 2377900000.0,
        "unit": "USD",
        "label": "Long-term Debt",
        "order": 810
      },
      "other_noncurrent_assets": {
        "value": 2955300000.0,
        "unit": "USD",
        "label": "Other Non-current Assets",
        "order": 350
      },
      "current_assets": {
        "value": 2905600000.0,
        "unit": "USD",
        "label": "Current Assets",
        "order": 200
      },
      "wages": {
        "value": 224400000.0,
        "unit": "USD",
        "label": "Wages",
        "order": 730
      },
      "liabilities": {
        "value": 5722700000.0,
        "unit": "USD",
        "label": "Liabilities",
        "order": 600
      },
      "inventory": {
        "value": 860700000.0,
        "unit": "USD",
        "label": "Inventory",
        "order": 230
      },
      "noncurrent_assets": {
        "value": 3674900000.0,
        "unit": "USD",
        "label": "Noncurrent Assets",
        "order": 300
      },
      "intangible_assets": {
        "value": 719600000.0,
        "unit": "USD",
        "label": "Intangible Assets",
        "order": 330
      },
      "noncurrent_liabilities": {
        "value": 4165800000.0,
        "unit": "USD",
        "label": "Noncurrent Liabilities",
        "order": 800
      },
      "assets": {
        "value": 6580500000.0,
        "unit": "USD",
        "label": "Assets",
        "order": 100
      },
      "current_liabilities": {
        "value": 1556900000.0,
        "unit": "USD",
        "label": "Current Liabilities",
        "order": 700
      },
      "other_noncurrent_liabilities": {
        "value": 1787900000.0,
        "unit": "USD",
        "label": "Other Non-current Liabilities",
        "order": 820
      },
      "accounts_payable": {
        "value": 456100000.0,
        "unit": "USD",
        "label": "Accounts Payable",
        "order": 710
      },
      "other_current_assets": {
        "value": 1911100000.0,
        "unit": "USD",
        "label": "Other Current Assets",
        "order": 250
      },
      "liabilities_and_equity": {
        "value": 6580500000.0,
        "unit": "USD",
        "label": "Liabilities And Equity",
        "order": 1900
      }
    }
  }
}