{
  "start_date": "2025-01-01",
  "end_date": "2025-12-31",
  "filing_date": "2026-02-11",
  "acceptance_datetime": "2026-02-11T12:02:15Z",
  "timeframe": "annual",
  "fiscal_period": "FY",
  "fiscal_year": "2025",
  "cik": "0001611547",
  "sic": "6500",
  "tickers": [
    "UE"
  ],
  "company_name": "Urban Edge Properties",
  "source_filing_url": "https://api.polygon.io/v1/reference/sec/filings/0001611547-26-000022",
  "source_filing_file_url": "http://api.polygon.io/v1/reference/sec/filings/0001611547-26-000022/files/ue-20251231_htm.xml",
  "financials": {
    "balance_sheet": {
      "equity": {
        "value": 1376472000.0,
        "unit": "USD",
        "label": "Equity",
        "order": 1400
      },
      "liabilities": {
        "value": 1935399000.0,
        "unit": "USD",
        "label": "Liabilities",
        "order": 600
      },
      "current_liabilities": {
        "value": 1935399000.0,
        "unit": "USD",
        "label": "Current Liabilities",
        "order": 700
      },
      "current_assets": {
        "value": 3311871000.0,
        "unit": "USD",
        "label": "Current Assets",
        "order": 200
      },
      "noncurrent_liabilities": {
        "value": 0,
        "unit": "USD",
        "label": "Noncurrent Liabilities",
        "order": 800
      },
      "equity_attributable_to_parent": {
        "value": 1376472000.0,
        "unit": "USD",
        "label": "Equity Attributable To Parent",
        "order": 1600
      },
      "liabilities_and_equity": {
        "value": 3311871000.0,
        "unit": "USD",
        "label": "Liabilities And Equity",
        "order": 1900
      },
      "noncurrent_assets": {
        "value": 0,
        "unit": "USD",
        "label": "Noncurrent Assets",
        "order": 300
      },
      "equity_attributable_to_noncontrolling_interest": {
        "value": 0,
        "unit": "USD",
        "label": "Equity Attributable To Noncontrolling Interest",
        "order": 1500
      },
      "assets": {
        "value": 3311871000.0,
        "unit": "USD",
        "label": "Assets",
        "order": 100
      }
    },
    "cash_flow_statement": {
      "net_cash_flow_from_financing_activities": {
        "value": -118889000.0,
        "unit": "USD",
        "label": "Net Cash Flow From Financing Activities",
        "order": 700
      },
      "net_cash_flow_from_financing_activities_continuing": {
        "value": -118889000.0,
        "unit": "USD",
        "label": "Net Cash Flow From Financing Activities, Continuing",
        "order": 800
      },
      "net_cash_flow_from_investing_activities_continuing": {
        "value": -75605000.0,
        "unit": "USD",
        "label": "Net Cash Flow From Investing Activities, Continuing",
        "order": 500
      },
      "net_cash_flow_continuing": {
        "value": -11775000.0,
        "unit": "USD",
        "label": "Net Cash Flow, Continuing",
        "order": 1200
      },
      "net_cash_flow": {
        "value": -11775000.0,
        "unit": "USD",
        "label": "Net Cash Flow",
        "order": 1100
      },
      "net_cash_flow_from_investing_activities": {
        "value": -75605000.0,
        "unit": "USD",
        "label": "Net Cash Flow From Investing Activities",
        "order": 400
      },
      "net_cash_flow_from_operating_activities": {
        "value": 182719000.0,
        "unit": "USD",
        "label": "Net Cash Flow From Operating Activities",
        "order": 100
      },
      "net_cash_flow_from_operating_activities_continuing": {
        "value": 182719000.0,
        "unit": "USD",
        "label": "Net Cash Flow From Operating Activities, Continuing",
        "order": 200
      }
    },
    "comprehensive_income": {
      "comprehensive_income_loss_attributable_to_parent": {
        "value": 92655000.0,
        "unit": "USD",
        "label": "Comprehensive Income/Loss Attributable To Parent",
        "order": 300
      },
      "other_comprehensive_income_loss_attributable_to_noncontrolling_interest": {
        "value": -48000,
        "unit": "USD",
        "label": "Other Comprehensive Income/Loss Attributable To Noncontrolling Interest",
        "order": 500
      },
      "comprehensive_income_loss_attributable_to_noncontrolling_interest": {
        "value": 3927000.0,
        "unit": "USD",
        "label": "Comprehensive Income/Loss Attributable To Noncontrolling Interest",
        "order": 200
      },
      "comprehensive_income_loss": {
        "value": 96582000.0,
        "unit": "USD",
        "label": "Comprehensive Income/Loss",
        "order": 100
      },
      "other_comprehensive_income_loss": {
        "value": -928000,
        "unit": "USD",
        "label": "Other Comprehensive Income/Loss",
        "order": 400
      }
    },
    "income_statement": {
      "net_income_loss_available_to_common_stockholders_basic": {
        "value": 93477000.0,
        "unit": "USD",
        "label": "Net Income/Loss Available To Common Stockholders, Basic",
        "order": 3700
      },
      "preferred_stock_dividends_and_other_adjustments": {
        "value": 58000,
        "unit": "USD",
        "label": "Preferred Stock Dividends And Other Adjustments",
        "order": 3900
      },
      "participating_securities_distributed_and_undistributed_earnings_loss_basic": {
        "value": 116000,
        "unit": "USD",
        "label": "Participating Securities, Distributed And Undistributed Earnings/Loss, Basic",
        "order": 3800
      },
      "net_income_loss_attributable_to_noncontrolling_interest": {
        "value": 3975000.0,
        "unit": "USD",
        "label": "Net Income/Loss Attributable To Noncontrolling Interest",
        "order": 3300
      },
      "other_operating_expenses": {
        "value": 232658000.0,
        "unit": "USD",
        "label": "Other Operating Expenses",
        "order": 1040
      },
      "interest_and_debt_expense": {
        "value": 78232000.0,
        "unit": "USD",
        "label": "Interest And Debt Expense",
        "order": 2500
      },
      "depreciation_and_amortization": {
        "value": 139166000.0,
        "unit": "USD",
        "label": "Depreciation and Amortization",
        "order": 1020
      },
      "diluted_average_shares": {
        "value": 125907000.0,
        "unit": "shares",
        "label": "Diluted Average Shares",
        "order": 4500
      },
      "benefits_costs_expenses": {
        "value": 371824000.0,
        "unit": "USD",
        "label": "Benefits Costs and Expenses",
        "order": 200
      },
      "undistributed_earnings_loss_allocated_to_participating_securities_basic": {
        "value": 58000,
        "unit": "USD",
        "label": "Undistributed Earnings/Loss Allocated To Participating Securities, Basic",
        "order": 4100
      },
      "diluted_earnings_per_share": {
        "value": 0.74,
        "unit": "USD / shares",
        "label": "Diluted Earnings Per Share",
        "order": 4300
      },
      "net_income_loss_attributable_to_nonredeemable_noncontrolling_interest": {
        "value": -1017000.0,
        "unit": "USD",
        "label": "Net Income/Loss Attributable To Nonredeemable Noncontrolling Interest",
        "order": 3400
      },
      "net_income_loss_attributable_to_redeemable_noncontrolling_interest": {
        "value": 4992000.0,
        "unit": "USD",
        "label": "Net Income/Loss Attributable To Redeemable Noncontrolling Interest",
        "order": 3600
      },
      "net_income_loss_attributable_to_parent": {
        "value": 93535000.0,
        "unit": "USD",
        "label": "Net Income/Loss Attributable To Parent",
        "order": 3500
      },
      "net_income_loss": {
        "value": 97510000.0,
        "unit": "USD",
        "label": "Net Income/Loss",
        "order": 3200
      },
      "basic_average_shares": {
        "value": 125686000.0,
        "unit": "shares",
        "label": "Basic Average Shares",
        "order": 4400
      },
      "income_loss_from_continuing_operations_before_tax": {
        "value": 100111000.0,
        "unit": "USD",
        "label": "Income/Loss From Continuing Operations Before Tax",
        "order": 1500
      },
      "basic_earnings_per_share": {
        "value": 0.74,
        "unit": "USD / shares",
        "label": "Basic Earnings Per Share",
        "order": 4200
      },
      "revenues": {
        "value": 471935000.0,
        "unit": "USD",
        "label": "Revenues",
        "order": 100
      },
      "income_tax_expense_benefit_current": {
        "value": 260000,
        "unit": "USD",
        "label": "Income Tax Expense/Benefit, Current",
        "order": 2300
      },
      "operating_income_loss": {
        "value": 100111000.0,
        "unit": "USD",
        "label": "Operating Income/Loss",
        "order": 1100
      },
      "income_tax_expense_benefit": {
        "value": 2601000.0,
        "unit": "USD",
        "label": "Income Tax Expense/Benefit",
        "order": 2200
      },
      "income_tax_expense_benefit_deferred": {
        "value": 2341000.0,
        "unit": "USD",
        "label": "Income Tax Expense/Benefit, Deferred",
        "order": 2400
      },
      "costs_and_expenses": {
        "value": 371824000.0,
        "unit": "USD",
        "label": "Costs And Expenses",
        "order": 600
      },
      "common_stock_dividends": {
        "value": 0.76,
        "unit": "USD / shares",
        "label": "Common Stock Dividends",
        "order": 4600
      },
      "operating_expenses": {
        "value": 371824000.0,
        "unit": "USD",
        "label": "Operating Expenses",
        "order": 1000
      },
      "income_loss_from_continuing_operations_after_tax": {
        "value": 97510000.0,
        "unit": "USD",
        "label": "Income/Loss From Continuing Operations After Tax",
        "order": 1400
      }
    }
  }
}